PDFCompareTrueDiff/__init__.py
PDFCompareTrueDiff-1.0.1.dist-info/LICENSE
PDFCompareTrueDiff-1.0.1.dist-info/METADATA
PDFCompareTrueDiff-1.0.1.dist-info/WHEEL
PDFCompareTrueDiff-1.0.1.dist-info/top_level.txt
PDFCompareTrueDiff-1.0.1.dist-info/RECORD
