Metadata-Version: 2.1
Name: PDFCompareTrueDiff
Version: 1.0.1
Summary: A PDF comparison tool which helps to view the differences side-by-side
Author: Datahub Technologies R&D PVT LTD
Author-email: hari.k@datahubtechnologies.com
Maintainer: HK, Priya K.P, Merlin Nissi Babu
Maintainer-email: hari.k@datahubtechnologies.com, priya@datahubtechnologies.com, merlin.datahubtechnologies@gmail.com
License: MIT
Requires-Python: >=3.8
License-File: LICENSE
Requires-Dist: pdf2image (==1.16.0)
Requires-Dist: PyPDF2 (==2.9.0)
Requires-Dist: numpy (==1.23.2)
Requires-Dist: PyMuPDF (==1.20.1)
Requires-Dist: pdfminer.six (==20220524)
